squarematrixenhancedplotter/__init__.py
squarematrixenhancedplotter/core.py
square_matrix_enhanced_plotter-0.1.3.dist-info/LICENSE
square_matrix_enhanced_plotter-0.1.3.dist-info/METADATA
square_matrix_enhanced_plotter-0.1.3.dist-info/WHEEL
square_matrix_enhanced_plotter-0.1.3.dist-info/top_level.txt
square_matrix_enhanced_plotter-0.1.3.dist-info/RECORD
