Metadata-Version: 2.1
Name: square_matrix_enhanced_plotter
Version: 0.1.3
Summary: A Python package for enhanced plotting of square matrices with zoom and interaction capabilities.
Home-page: https://github.com/robertobalestri/Square-Matrix-Enhanced-Plotter-Python
Author: Roberto Balestri
Author-email: roberto.balestri2@unibo.it
Project-URL: Bug Tracker, https://github.com/robertobalestri/Square-Matrix-Enhanced-Plotter-Python
Project-URL: Source Code, https://github.com/robertobalestri/Square-Matrix-Enhanced-Plotter-Python
Keywords: matrix square matplotlib plot zoom interaction
Classifier: Programming Language :: Python :: 3
Classifier: License :: OSI Approved :: MIT License
Classifier: Operating System :: OS Independent
License-File: LICENSE
Requires-Dist: matplotlib
Requires-Dist: mplcursors
Requires-Dist: numpy
Requires-Dist: PyQT5
